astrocubelib/__init__.py
astrocubelib/functions.py
astrocubelib-1.2.0.data/scripts/cube.py
astrocubelib-1.2.0.data/scripts/cube_channelvel.py
astrocubelib-1.2.0.data/scripts/cube_fig.py
astrocubelib-1.2.0.data/scripts/cube_manga.py
astrocubelib-1.2.0.data/scripts/guimask.py
astrocubelib-1.2.0.data/scripts/guisplot.py
astrocubelib-1.2.0.data/scripts/mask.py
astrocubelib-1.2.0.data/scripts/plot_spec.py
astrocubelib-1.2.0.dist-info/LICENSE
astrocubelib-1.2.0.dist-info/METADATA
astrocubelib-1.2.0.dist-info/WHEEL
astrocubelib-1.2.0.dist-info/top_level.txt
astrocubelib-1.2.0.dist-info/RECORD
