Metadata-Version: 2.1
Name: astrocubelib
Version: 1.2.0
Summary: Utilities to handle astronomy data cube.
Home-page: https://gitlab.com/joseaher/astrocubelib
Author: J. A. Hernandez-Jimenez
Author-email: joseaher@gmail.com
License-File: LICENSE
